donno/__init__.py
donno/app.py
donno/blog.py
donno/config.py
donno/notes.py
donno/converters/__init__.py
donno/converters/joplin.py
donno-1.0.1.dist-info/LICENSE
donno-1.0.1.dist-info/METADATA
donno-1.0.1.dist-info/WHEEL
donno-1.0.1.dist-info/entry_points.txt
donno-1.0.1.dist-info/top_level.txt
donno-1.0.1.dist-info/RECORD
