Metadata-Version: 2.1
Name: donno
Version: 1.0.1
Summary: A simple note-taking CLI application
Home-page: https://github.com/leetschau/donno
Author: Li Chao
Author-email: clouds@isrc.iscas.ac.cn
License: UNKNOWN
Keywords: note pim
Platform: UNKNOWN
Classifier: Programming Language :: Python :: 3
Classifier: License :: OSI Approved :: MIT License
Classifier: Operating System :: OS Independent
Requires-Python: >=3.6
Requires-Dist: sh (>=1.14.0)
Requires-Dist: fire (>=0.3.1)
